{"binding":{"account_id":"act_exact-id","ad_id":"returned-ad-id","ad_set_id":"exact-ad-set-id","artifact_sha256":"ffffffffffffffffffffffffffffffffffffffffffffffffffffffffffffffff","campaign_id":"exact-campaign-id","creative_id":"returned-creative-id","item_key":"manifest-item-key","status":"PAUSED"},"observed_at":"2026-07-10T12:00:00Z","provider":"meta_ads_mcp","provider_response":{"id":"returned-ad-id","status":"PAUSED"},"schema":"creative-forge/meta-ad-readback@1","tool":"replace-with-manifest-readback-tool"}
